<annotation>
	<folder>compress</folder>
	<filename>130.jpg</filename>
	<path>/home/sudz/Desktop/vex_parts-v3/parts/bearing_flat/compress/130.jpg</path>
	<source>
		<database>Unknown</database>
	</source>
	<size>
		<width>800</width>
		<height>600</height>
		<depth>3</depth>
	</size>
	<segmented>0</segmented>
	<object>
		<name>bearing_flat</name>
		<pose>Unspecified</pose>
		<truncated>0</truncated>
		<difficult>0</difficult>
		<bndbox>
			<xmin>249</xmin>
			<ymin>381</ymin>
			<xmax>300</xmax>
			<ymax>490</ymax>
		</bndbox>
	</object>
</annotation>