<annotation>
	<folder>compress</folder>
	<filename>14.jpg</filename>
	<path>/home/sudz/Desktop/vex_parts-v3/parts/bearing_flat/compress/14.jpg</path>
	<source>
		<database>Unknown</database>
	</source>
	<size>
		<width>800</width>
		<height>600</height>
		<depth>3</depth>
	</size>
	<segmented>0</segmented>
	<object>
		<name>bearing_flat</name>
		<pose>Unspecified</pose>
		<truncated>0</truncated>
		<difficult>0</difficult>
		<bndbox>
			<xmin>236</xmin>
			<ymin>274</ymin>
			<xmax>511</xmax>
			<ymax>430</ymax>
		</bndbox>
	</object>
</annotation>