<annotation>
	<folder>compress</folder>
	<filename>49.jpg</filename>
	<path>gs://sudz/parts_sorter/parts/bearing_flat/compress/49.jpg</path>
	<source>
		<database>Unknown</database>
	</source>
	<size>
		<width>800</width>
		<height>600</height>
		<depth>3</depth>
	</size>
	<segmented>0</segmented>
	<object>
		<name>bearing_flat</name>
		<pose>Unspecified</pose>
		<truncated>0</truncated>
		<difficult>0</difficult>
		<bndbox>
			<xmin>439</xmin>
			<ymin>102</ymin>
			<xmax>664</xmax>
			<ymax>406</ymax>
		</bndbox>
	</object>
</annotation>