<annotation>
	<folder>compress</folder>
	<filename>196.jpg</filename>
	<path>/home/sudz/Desktop/vex_parts-v3/parts/bigspacer/compress/196.jpg</path>
	<source>
		<database>Unknown</database>
	</source>
	<size>
		<width>400</width>
		<height>300</height>
		<depth>3</depth>
	</size>
	<segmented>0</segmented>
	<object>
		<name>1.0spacer</name>
		<pose>Unspecified</pose>
		<truncated>0</truncated>
		<difficult>0</difficult>
		<bndbox>
			<xmin>107</xmin>
			<ymin>158</ymin>
			<xmax>146</xmax>
			<ymax>198</ymax>
		</bndbox>
	</object>
	<object>
		<name>1.0spacer</name>
		<pose>Unspecified</pose>
		<truncated>0</truncated>
		<difficult>0</difficult>
		<bndbox>
			<xmin>226</xmin>
			<ymin>144</ymin>
			<xmax>262</xmax>
			<ymax>176</ymax>
		</bndbox>
	</object>
	<object>
		<name>1.0spacer</name>
		<pose>Unspecified</pose>
		<truncated>0</truncated>
		<difficult>0</difficult>
		<bndbox>
			<xmin>254</xmin>
			<ymin>47</ymin>
			<xmax>281</xmax>
			<ymax>77</ymax>
		</bndbox>
	</object>
	<object>
		<name>1.0spacer</name>
		<pose>Unspecified</pose>
		<truncated>0</truncated>
		<difficult>0</difficult>
		<bndbox>
			<xmin>284</xmin>
			<ymin>2</ymin>
			<xmax>322</xmax>
			<ymax>26</ymax>
		</bndbox>
	</object>
	<object>
		<name>1.0spacer</name>
		<pose>Unspecified</pose>
		<truncated>0</truncated>
		<difficult>0</difficult>
		<bndbox>
			<xmin>169</xmin>
			<ymin>19</ymin>
			<xmax>207</xmax>
			<ymax>40</ymax>
		</bndbox>
	</object>
	<object>
		<name>1.0spacer</name>
		<pose>Unspecified</pose>
		<truncated>1</truncated>
		<difficult>0</difficult>
		<bndbox>
			<xmin>165</xmin>
			<ymin>1</ymin>
			<xmax>202</xmax>
			<ymax>17</ymax>
		</bndbox>
	</object>
	<object>
		<name>1.0spacer</name>
		<pose>Unspecified</pose>
		<truncated>1</truncated>
		<difficult>0</difficult>
		<bndbox>
			<xmin>382</xmin>
			<ymin>88</ymin>
			<xmax>400</xmax>
			<ymax>117</ymax>
		</bndbox>
	</object>
</annotation>