<annotation>
	<folder>images</folder>
	<filename>247.jpg</filename>
	<path>/home/sudz/Desktop/vex_parts-v2 (copy)/models/images/247.jpg</path>
	<source>
		<database>Unknown</database>
	</source>
	<size>
		<width>800</width>
		<height>600</height>
		<depth>3</depth>
	</size>
	<segmented>0</segmented>
	<object>
		<name>screw4</name>
		<pose>Unspecified</pose>
		<truncated>0</truncated>
		<difficult>0</difficult>
		<bndbox>
			<xmin>304</xmin>
			<ymin>269</ymin>
			<xmax>448</xmax>
			<ymax>453</ymax>
		</bndbox>
	</object>
</annotation>
